ptt/__init__.py
ptt/cleanup_topologies.py
ptt/convert_xy_to_gplates.py
ptt/documentation.py
ptt/remove_plate_rotations.py
ptt/resolve_topologies.py
ptt/ridge_spreading_rate.py
ptt/rotation_tools.py
ptt/separate_ridge_transform_segments.py
ptt/subduction_convergence.py
ptt/velocity_tools.py
ptt/Examples/data/Global_EarthByte_230-0Ma_GK07_AREPS.rot
ptt/Examples/data/Global_EarthByte_230-0Ma_GK07_AREPS_PlateBoundaries.gpmlz
ptt/Examples/data/Global_EarthByte_230-0Ma_GK07_AREPS_Topology_BuildingBlocks.gpmlz
ptt/Examples/data/Matthews_etal_GPC_2016_Coastlines.gpmlz
ptt/Examples/notebooks/plot_velocity_vectors.ipynb
ptt/Examples/notebooks/predict_using_chebyshev_2d.ipynb
ptt/Examples/notebooks/ridge_length_spreading_rates.ipynb
ptt/Examples/notebooks/sample_raster_along_subd_zone.ipynb
ptt/Examples/notebooks/subduction_obliquity.ipynb
ptt/Examples/notebooks/subduction_teeth.ipynb
ptt/utils/GPMLTools.py
ptt/utils/__init__.py
ptt/utils/call_system_command.py
ptt/utils/points_in_polygons.py
ptt/utils/points_spatial_tree.py
ptt/utils/proximity_query.py
ptt/utils/reconstruct_by_topologies.py
ptt/utils/subduction_teeth.py
PlateTectonicTools-0.3.dist-info/LICENSE
PlateTectonicTools-0.3.dist-info/METADATA
PlateTectonicTools-0.3.dist-info/WHEEL
PlateTectonicTools-0.3.dist-info/top_level.txt
PlateTectonicTools-0.3.dist-info/RECORD
