Metadata-Version: 2.1
Name: PlateTectonicTools
Version: 0.3
Summary: Python tools for plate tectonic research
Home-page: https://github.com/EarthByte/PlateTectonicTools
Author: John Cannon
Author-email: john.cannon@sydney.edu.au
License: UNKNOWN
Platform: UNKNOWN
Classifier: Programming Language :: Python :: 2
Classifier: Programming Language :: Python :: 2.7
Classifier: Programming Language :: Python :: 3
Requires-Python: >=2.7
License-File: LICENSE
Requires-Dist: numpy
